qteasy/__init__.py
qteasy/_arg_validators.py
qteasy/akfuncs.py
qteasy/backtest.py
qteasy/blender.py
qteasy/broker.py
qteasy/built_in.py
qteasy/configure.py
qteasy/core.py
qteasy/data_channels.py
qteasy/database.py
qteasy/datatables.py
qteasy/datatypes.py
qteasy/emfuncs.py
qteasy/errors.py
qteasy/evaluate.py
qteasy/finance.py
qteasy/history.py
qteasy/optimization.py
qteasy/qt_code.py
qteasy/qt_operator.py
qteasy/sinafuncs.py
qteasy/space.py
qteasy/strategy.py
qteasy/tafuncs.py
qteasy/trade_recording.py
qteasy/trader.py
qteasy/trader_cli.py
qteasy/trader_tui.py
qteasy/trading_util.py
qteasy/tsfuncs.py
qteasy/tui_style.tcss
qteasy/utilfuncs.py
qteasy/visual.py
qteasy-1.4.10.dist-info/licenses/LICENSE
qteasy-1.4.10.dist-info/METADATA
qteasy-1.4.10.dist-info/WHEEL
qteasy-1.4.10.dist-info/top_level.txt
qteasy-1.4.10.dist-info/RECORD
