Metadata-Version: 2.4
Name: qteasy
Version: 1.4.10
Summary: A fast quantitative investment tool kit
Home-page: https://github.com/shepherdpp/qteasy
Author: Jackie PENG
Author-email: jackie PENG <jackie.pengzhao@gmail.com>
Maintainer: Jackie PENG
Maintainer-email: jackie PENG <jackie.pengzhao@gmail.com>
License: Copyright <2019> <JACKIE PENG>
Project-URL: Homepage, https://github.com/shepherdpp/qteasy
Project-URL: Documentation, https://qteasy.readthedocs.io/zh/latest/
Project-URL: Issues, https://github.com/shepherdpp/qteasy/issues
Keywords: quantitative investment,quantitative trading,stock,finance,investment
Classifier: Development Status :: 4 - Beta
Classifier: Intended Audience :: Financial and Insurance Industry
Classifier: Intended Audience :: End Users/Desktop
Classifier: Intended Audience :: Other Audience
Classifier: License :: OSI Approved :: BSD License
Classifier: Programming Language :: Python
Classifier: Programming Language :: Python :: 3
Classifier: Programming Language :: Python :: 3.6
Classifier: Programming Language :: Python :: 3.7
Classifier: Programming Language :: Python :: 3.8
Classifier: Programming Language :: Python :: 3.9
Classifier: Programming Language :: Python :: 3.10
Classifier: Programming Language :: Python :: 3.11
Classifier: Programming Language :: Python :: 3.12
Classifier: Operating System :: MacOS
Classifier: Operating System :: Microsoft :: Windows
Classifier: Topic :: Documentation :: Sphinx
Classifier: Topic :: Office/Business :: Financial
Classifier: Topic :: Office/Business :: Financial :: Investment
Requires-Python: <3.13,>=3.7
License-File: LICENSE
Requires-Dist: pandas>=1.5.0
Requires-Dist: numpy>=1.18.1
Requires-Dist: numba>=0.47.0
Requires-Dist: tushare>=1.2.89
Requires-Dist: pymysql>=1.1.1
Requires-Dist: dbutils>=3.0.0
Requires-Dist: mplfinance
Requires-Dist: rich>=10.0.0
Requires-Dist: textual
Provides-Extra: talib
Requires-Dist: ta-lib; extra == "talib"
Provides-Extra: feather
Requires-Dist: pyarrow>=3; extra == "feather"
Provides-Extra: dev
Requires-Dist: ta-lib; extra == "dev"
Requires-Dist: pymysql>=1.1.1; extra == "dev"
Requires-Dist: dbutils>=3.0.0; extra == "dev"
Requires-Dist: pyarrow>=3; extra == "dev"
Dynamic: license-file
